{
  "axe_double": iron,
  "hammer_suns_grace": diamond,
  "staff_battlestaff_of_terror": iron,
  "bow_snow_bow": wood,
  "sickle_sickle": iron,
  "bow_haunted_bow": wood,
  "sword_dancers_sword": iron,
  "pick_diamond_pickaxe_var": diamond,
  "bow_green_menace": wood,
  "bow_pink_scoundrel": wood,
  "axe": iron,
  "bow_winters_touch": wood,
  "dagger_resolute_tempest_knife": iron,
  "bow_sabrewing": wood,
  "sword_freezing_foil": diamond,
  "bow_soul_bow": wood,
  "sword_claymore": iron,
  "hammer_bone_cudgel": diamond,
  "dagger_dagger": iron,
  "staff_battlestaff": wood,
  "bow_masters_bow": wood,
  "sword_iron_sword_var": iron,
  "pick_mountaineer_pick": iron,
  "sword_mechanized_sawblade": diamond,
  "spear_glaive": iron,
  "sword_coral_blade": iron,
  "dagger_chill_gale_knife": iron,
  "hammer_great": iron,
  "bow_love_spell_bow": wood,
  "gauntlet_fighters_bindings": iron,
  "hammer_mace": iron,
  "sword_cutlass": iron,
  "sword_truthseeker": iron,
  "sickle_last_laugh_silver": gold,
  "spear_whispering_spear": iron,
  "sword_katana": iron,
  "bow_guardian_bow": wood,
  "bow_burst_gale_bow": wood,
  "sword_frost_slayer": diamond,
  "bow_weeping_vine_bow": wood,
  "dagger_eternal_knife": diamond,
  "dagger_tempest_knife": iron,
  "staff_growing_staff": iron,
  "bow_lost_souls": wood,
  "bow_shivering_bow": wood,
  "dagger_shear_dagger": iron,
  "sword_rapier": iron,
  "dagger_fangs_of_frost": iron,
  "bow_twisting_vine_bow": wood,
  "sword_nameless_blade": diamond,
  "bow_trickbow": wood,
  "whip_vine_whip": iron,
  "sword_sponge_striker": diamond,
  "axe_encrusted_anchor": diamond,
  "bow_power_bow": wood,
  "bow_red_snake": wood,
  "dagger_moon": iron,
  "hammer_flail": iron,
  "sword_masters_katana": diamond,
  "gauntlet_maulers": diamond,
  "spear_grave_bane": iron,
  "sword_diamond_sword_var": diamond,
  "spear_fortune": gold,
  "whip_whip": iron,
  "sword_beestinger": diamond,
  "dagger_soul_knife": iron,
  "bow_bonebow": wood,
  "axe_firebrand": diamond,
  "axe_cursed": iron,
  "spear_spear": iron,
  "hammer_gravity": diamond,
  "sword_dark_katana": netherite,
  "sword_heartstealer": diamond,
  "hammer_boneclub": iron,
  "gauntlet_gauntlet": iron,
  "bow_nocturnal_bow": wood,
  "bow_elite_power_bow": wood,
  "sickle_frost_scythe": iron,
  "bow_mechanical_shortbow": wood,
  "sickle_jailors_scythe": iron,
  "gauntlet_soul_fists": netherite,
  "pick_hailing_pinnacle": diamond,
  "hammer_stormlander": diamond,
  "sword_broadsword": iron,
  "bow_ancient_bow": wood,
  "spear_venom_glaive": iron,
  "bow_longbow": wood,
  "sickle_soul_scythe": diamond,
  "bow_wind_bow": wood,
  "sword_hawkbrand": iron,
  "axe_whirlwind": iron,
  "sickle_nightmares_bite": iron,
  "sword_great_axeblade": iron,
  "axe_highland": iron,
  "sickle_last_laugh_gold": gold,
  "sword_broken_sawblade": iron,
  "bow_hunting_bow": wood,
  "bow_shortbow": wood,
  "bow_purple_storm": wood,
  "bow_echo_of_the_valley": wood,
  "bow_hunters_promise": wood,
  "axe_anchor": iron,
  "pick_howling_pick": iron
}